[
    {
        "time_stamp": "2024-09-20 21:09:48",
        "num_of_customers": 1,
        "start_time": "2024-09-20 16:20:45",
        "expected_end_time": "2024-09-20 19:30:00",
        "latitude": 47.30282624448333,
        "longitude": -70.63726686915186,
        "outage_status": "Crew on the way",
        "ignore": "",
        "cause_of_outage": null,
        "municipality": "6771",
        "code": ""
    },
    {
        "time_stamp": "2024-09-20 21:09:48",
        "num_of_customers": 35,
        "start_time": "2024-09-20 16:13:27",
        "expected_end_time": "2024-09-20 18:15:00",
        "latitude": 45.866913360546896,
        "longitude": -74.45917299702482,
        "outage_status": "Crew at work",
        "ignore": "",
        "cause_of_outage": null,
        "municipality": "9473",
        "code": ""
    },
    {
        "time_stamp": "2024-09-20 21:09:48",
        "num_of_customers": 6,
        "start_time": "2024-09-20 16:31:44",
        "expected_end_time": "2024-09-20 18:30:00",
        "latitude": 45.543357330552354,
        "longitude": -73.7059615041136,
        "outage_status": "NA",
        "ignore": "",
        "cause_of_outage": null,
        "municipality": "1000",
        "code": ""
    },
    {
        "time_stamp": "2024-09-20 21:09:48",
        "num_of_customers": 3,
        "start_time": "2024-09-20 14:06:35",
        "expected_end_time": "2024-09-20 18:45:00",
        "latitude": 45.01701885426256,
        "longitude": -73.89240410959138,
        "outage_status": "Crew on the way",
        "ignore": "",
        "cause_of_outage": null,
        "municipality": "2345",
        "code": ""
    },
    {
        "time_stamp": "2024-09-20 21:09:48",
        "num_of_customers": 1,
        "start_time": "2024-09-20 14:41:13",
        "expected_end_time": "",
        "latitude": 47.00364384145053,
        "longitude": -71.19067777702607,
        "outage_status": "Crew on the way",
        "ignore": "",
        "cause_of_outage": null,
        "municipality": "8545",
        "code": ""
    },
    {
        "time_stamp": "2024-09-20 21:09:48",
        "num_of_customers": 1876,
        "start_time": "2024-09-20 16:19:39",
        "expected_end_time": "2024-09-20 18:15:00",
        "latitude": 45.531910614236885,
        "longitude": -73.64011417757035,
        "outage_status": "Crew on the way",
        "ignore": "3",
        "cause_of_outage": "Accident or incident",
        "municipality": "1000",
        "code": ""
    },
    {
        "time_stamp": "2024-09-20 21:09:48",
        "num_of_customers": 32,
        "start_time": "2024-09-20 09:19:02",
        "expected_end_time": "2024-09-20 17:15:00",
        "latitude": 45.54318391033733,
        "longitude": -73.70031228568237,
        "outage_status": "Crew at work",
        "ignore": "6",
        "cause_of_outage": null,
        "municipality": "1000",
        "code": ""
    },
    {
        "time_stamp": "2024-09-20 21:09:48",
        "num_of_customers": 41,
        "start_time": "2024-09-20 09:19:45",
        "expected_end_time": "2024-09-20 17:15:00",
        "latitude": 45.543598124336526,
        "longitude": -73.70148638314667,
        "outage_status": "Crew at work",
        "ignore": "6",
        "cause_of_outage": null,
        "municipality": "1000",
        "code": ""
    }
]