[
    {
        "time_stamp": "2025-06-07 05:26:44",
        "num_of_customers": 2,
        "start_time": "2025-06-06 22:38:47",
        "expected_end_time": "2025-06-07 03:00:00",
        "latitude": 46.42021899863346,
        "longitude": -70.5210474575894,
        "outage_status": "Crew at work",
        "ignore": "1",
        "cause_of_outage": "Equipment failure",
        "municipality": "4107",
        "code": ""
    },
    {
        "time_stamp": "2025-06-07 05:26:44",
        "num_of_customers": 32,
        "start_time": "2025-06-06 19:49:09",
        "expected_end_time": "2025-06-07 08:15:00",
        "latitude": 46.8245955268936,
        "longitude": -71.23112872936224,
        "outage_status": "Crew at work",
        "ignore": "1",
        "cause_of_outage": "Equipment failure",
        "municipality": "5410",
        "code": ""
    },
    {
        "time_stamp": "2025-06-07 05:26:44",
        "num_of_customers": 10,
        "start_time": "2025-06-06 22:16:13",
        "expected_end_time": "2025-06-07 02:15:00",
        "latitude": 45.43175837698098,
        "longitude": -73.29853641493327,
        "outage_status": "Crew on the way",
        "ignore": "",
        "cause_of_outage": null,
        "municipality": "1718",
        "code": ""
    },
    {
        "time_stamp": "2025-06-07 05:26:44",
        "num_of_customers": 92,
        "start_time": "2025-06-06 21:27:58",
        "expected_end_time": "2025-06-07 03:15:00",
        "latitude": 46.191108216420425,
        "longitude": -74.04831268137394,
        "outage_status": "Crew at work",
        "ignore": "5",
        "cause_of_outage": "Equipment failure",
        "municipality": "4977",
        "code": ""
    },
    {
        "time_stamp": "2025-06-07 05:26:44",
        "num_of_customers": 74,
        "start_time": "2025-06-06 23:49:26",
        "expected_end_time": "2025-06-07 01:45:00",
        "latitude": 45.69305209826393,
        "longitude": -73.65916950919836,
        "outage_status": "Crew at work",
        "ignore": "4",
        "cause_of_outage": "Accident or incident",
        "municipality": "9160",
        "code": ""
    },
    {
        "time_stamp": "2025-06-07 05:26:44",
        "num_of_customers": 9,
        "start_time": "2025-06-07 00:25:21",
        "expected_end_time": "2025-06-07 02:30:00",
        "latitude": 45.467760702547615,
        "longitude": -72.66307702248591,
        "outage_status": "Crew on the way",
        "ignore": "",
        "cause_of_outage": null,
        "municipality": "8947",
        "code": ""
    },
    {
        "time_stamp": "2025-06-07 05:26:44",
        "num_of_customers": 1,
        "start_time": "2025-06-06 23:48:32",
        "expected_end_time": "2025-06-07 01:45:00",
        "latitude": 45.794006196659915,
        "longitude": -70.63057796100428,
        "outage_status": "NA",
        "ignore": "",
        "cause_of_outage": null,
        "municipality": "6828",
        "code": ""
    },
    {
        "time_stamp": "2025-06-07 05:26:44",
        "num_of_customers": 9,
        "start_time": "2025-06-06 23:59:23",
        "expected_end_time": "2025-06-07 02:00:00",
        "latitude": 45.82495228150547,
        "longitude": -73.63336409253952,
        "outage_status": "Work assigned",
        "ignore": "",
        "cause_of_outage": null,
        "municipality": "8020",
        "code": ""
    }
]