[
    {
        "time_stamp": "2025-06-30 19:21:58",
        "num_of_customers": 2,
        "start_time": "2025-06-30 13:50:34",
        "expected_end_time": "2025-06-30 15:45:00",
        "latitude": 46.832843232034065,
        "longitude": -72.2849624493683,
        "outage_status": "Crew on the way",
        "ignore": "",
        "cause_of_outage": null,
        "municipality": "8230",
        "code": ""
    },
    {
        "time_stamp": "2025-06-30 19:21:58",
        "num_of_customers": 4,
        "start_time": "2025-06-30 10:05:32",
        "expected_end_time": "2025-06-30 21:15:00",
        "latitude": 53.77569466943363,
        "longitude": -78.88723279396478,
        "outage_status": "Work assigned",
        "ignore": "",
        "cause_of_outage": null,
        "municipality": "1852",
        "code": ""
    },
    {
        "time_stamp": "2025-06-30 19:21:58",
        "num_of_customers": 3,
        "start_time": "2025-06-30 13:56:13",
        "expected_end_time": "2025-06-30 16:00:00",
        "latitude": 48.634626368712816,
        "longitude": -71.71070251629375,
        "outage_status": "Crew at work",
        "ignore": "5",
        "cause_of_outage": "Accident or incident",
        "municipality": "2021",
        "code": ""
    },
    {
        "time_stamp": "2025-06-30 19:21:58",
        "num_of_customers": 4,
        "start_time": "2025-06-30 14:18:35",
        "expected_end_time": "2025-06-30 16:15:00",
        "latitude": 46.30226156937159,
        "longitude": -70.96849603087502,
        "outage_status": "Crew on the way",
        "ignore": "",
        "cause_of_outage": null,
        "municipality": "6765",
        "code": ""
    },
    {
        "time_stamp": "2025-06-30 19:21:58",
        "num_of_customers": 10,
        "start_time": "2025-06-30 11:17:57",
        "expected_end_time": "",
        "latitude": 46.67819040436967,
        "longitude": -72.612389032228,
        "outage_status": "NA",
        "ignore": "",
        "cause_of_outage": null,
        "municipality": "8215",
        "code": ""
    },
    {
        "time_stamp": "2025-06-30 19:21:58",
        "num_of_customers": 44,
        "start_time": "2025-06-30 11:20:43",
        "expected_end_time": "2025-06-30 17:45:00",
        "latitude": 46.61994928238852,
        "longitude": -72.75898442161079,
        "outage_status": "Work assigned",
        "ignore": "5",
        "cause_of_outage": "Damage due to vegetation",
        "municipality": "2435",
        "code": ""
    },
    {
        "time_stamp": "2025-06-30 19:21:58",
        "num_of_customers": 2,
        "start_time": "2025-06-30 14:13:40",
        "expected_end_time": "2025-06-30 16:15:00",
        "latitude": 46.578576890564655,
        "longitude": -70.79930529283259,
        "outage_status": "NA",
        "ignore": "",
        "cause_of_outage": null,
        "municipality": "8602",
        "code": ""
    },
    {
        "time_stamp": "2025-06-30 19:21:58",
        "num_of_customers": 3,
        "start_time": "2025-06-30 14:03:20",
        "expected_end_time": "2025-06-30 18:15:00",
        "latitude": 46.13557097483463,
        "longitude": -70.67642467904102,
        "outage_status": "Crew on the way",
        "ignore": "",
        "cause_of_outage": null,
        "municipality": "6840",
        "code": ""
    },
    {
        "time_stamp": "2025-06-30 19:21:58",
        "num_of_customers": 11,
        "start_time": "2025-06-30 10:48:48",
        "expected_end_time": "2025-06-30 15:45:00",
        "latitude": 46.373505155235804,
        "longitude": -72.57034930603756,
        "outage_status": "Crew at work",
        "ignore": "3",
        "cause_of_outage": "Accident or incident",
        "municipality": "1652",
        "code": ""
    },
    {
        "time_stamp": "2025-06-30 19:21:58",
        "num_of_customers": 1,
        "start_time": "2025-06-30 14:13:50",
        "expected_end_time": "2025-06-30 16:15:00",
        "latitude": 45.577839181572536,
        "longitude": -73.45541438486039,
        "outage_status": "Crew on the way",
        "ignore": "",
        "cause_of_outage": null,
        "municipality": "1460",
        "code": ""
    },
    {
        "time_stamp": "2025-06-30 19:21:58",
        "num_of_customers": 5,
        "start_time": "2025-06-30 14:20:07",
        "expected_end_time": "2025-06-30 16:15:00",
        "latitude": 45.581197868291646,
        "longitude": -73.7803784200308,
        "outage_status": "Crew on the way",
        "ignore": "",
        "cause_of_outage": null,
        "municipality": "2261",
        "code": ""
    },
    {
        "time_stamp": "2025-06-30 19:21:58",
        "num_of_customers": 2,
        "start_time": "2025-06-30 13:21:33",
        "expected_end_time": "2025-06-30 15:15:00",
        "latitude": 45.16873490843104,
        "longitude": -72.05577449262226,
        "outage_status": "Crew on the way",
        "ignore": "",
        "cause_of_outage": null,
        "municipality": "1179",
        "code": ""
    },
    {
        "time_stamp": "2025-06-30 19:21:58",
        "num_of_customers": 15,
        "start_time": "2025-06-30 13:26:18",
        "expected_end_time": "2025-06-30 15:30:00",
        "latitude": 45.46303099507232,
        "longitude": -75.74964238911653,
        "outage_status": "Crew on the way",
        "ignore": "",
        "cause_of_outage": null,
        "municipality": "2642",
        "code": ""
    },
    {
        "time_stamp": "2025-06-30 19:21:58",
        "num_of_customers": 26,
        "start_time": "2025-06-30 14:53:33",
        "expected_end_time": "",
        "latitude": 48.23100502480286,
        "longitude": -79.01273400221069,
        "outage_status": "Work assigned",
        "ignore": "",
        "cause_of_outage": null,
        "municipality": "5647",
        "code": ""
    },
    {
        "time_stamp": "2025-06-30 19:21:58",
        "num_of_customers": 1,
        "start_time": "2025-06-30 14:54:03",
        "expected_end_time": "",
        "latitude": 46.904533586930086,
        "longitude": -70.02006076005615,
        "outage_status": "Crew on the way",
        "ignore": "",
        "cause_of_outage": null,
        "municipality": "7542",
        "code": ""
    },
    {
        "time_stamp": "2025-06-30 19:21:58",
        "num_of_customers": 523,
        "start_time": "2025-06-30 13:18:13",
        "expected_end_time": "2025-06-30 20:15:00",
        "latitude": 46.124854006656285,
        "longitude": -74.62420434142449,
        "outage_status": "Crew at work",
        "ignore": "5",
        "cause_of_outage": "Accident or incident",
        "municipality": "7305",
        "code": ""
    },
    {
        "time_stamp": "2025-06-30 19:21:58",
        "num_of_customers": 2,
        "start_time": "2025-06-30 14:51:21",
        "expected_end_time": "",
        "latitude": 45.5588859465152,
        "longitude": -73.33519366271956,
        "outage_status": "Crew at work",
        "ignore": "1",
        "cause_of_outage": "Equipment failure",
        "municipality": "6210",
        "code": ""
    },
    {
        "time_stamp": "2025-06-30 19:21:58",
        "num_of_customers": 121,
        "start_time": "2025-06-30 12:57:35",
        "expected_end_time": "2025-06-30 17:00:00",
        "latitude": 45.48149067224317,
        "longitude": -73.63565243367256,
        "outage_status": "Crew at work",
        "ignore": "6",
        "cause_of_outage": null,
        "municipality": "0103",
        "code": ""
    },
    {
        "time_stamp": "2025-06-30 19:21:58",
        "num_of_customers": 61,
        "start_time": "2025-06-30 12:58:08",
        "expected_end_time": "2025-06-30 17:00:00",
        "latitude": 45.48085345654686,
        "longitude": -73.6331786627492,
        "outage_status": "Crew at work",
        "ignore": "6",
        "cause_of_outage": null,
        "municipality": "0217",
        "code": ""
    },
    {
        "time_stamp": "2025-06-30 19:21:58",
        "num_of_customers": 28,
        "start_time": "2025-06-30 12:59:21",
        "expected_end_time": "2025-06-30 17:00:00",
        "latitude": 45.48148201107777,
        "longitude": -73.63457178513919,
        "outage_status": "Crew at work",
        "ignore": "6",
        "cause_of_outage": null,
        "municipality": "0217",
        "code": ""
    },
    {
        "time_stamp": "2025-06-30 19:21:58",
        "num_of_customers": 4,
        "start_time": "2025-06-30 14:58:59",
        "expected_end_time": "",
        "latitude": 48.26816780702891,
        "longitude": -79.01913136988517,
        "outage_status": "Crew on the way",
        "ignore": "",
        "cause_of_outage": null,
        "municipality": "5647",
        "code": ""
    },
    {
        "time_stamp": "2025-06-30 19:21:58",
        "num_of_customers": 1,
        "start_time": "2025-06-30 13:43:06",
        "expected_end_time": "2025-06-30 15:45:00",
        "latitude": 48.25888722800192,
        "longitude": -69.62562480947149,
        "outage_status": "NA",
        "ignore": "",
        "cause_of_outage": null,
        "municipality": "1374",
        "code": ""
    },
    {
        "time_stamp": "2025-06-30 19:21:58",
        "num_of_customers": 42,
        "start_time": "2025-06-30 13:46:00",
        "expected_end_time": "2025-06-30 17:30:00",
        "latitude": 45.386042529001486,
        "longitude": -73.32958623567343,
        "outage_status": "Crew at work",
        "ignore": "6",
        "cause_of_outage": null,
        "municipality": "1670",
        "code": ""
    },
    {
        "time_stamp": "2025-06-30 19:21:58",
        "num_of_customers": 1,
        "start_time": "2025-06-30 15:00:29",
        "expected_end_time": "",
        "latitude": 45.94200828279067,
        "longitude": -75.96386806982612,
        "outage_status": "NA",
        "ignore": "",
        "cause_of_outage": null,
        "municipality": "1194",
        "code": ""
    },
    {
        "time_stamp": "2025-06-30 19:21:58",
        "num_of_customers": 4,
        "start_time": "2025-06-30 12:05:33",
        "expected_end_time": "2025-06-30 21:15:00",
        "latitude": 53.77373884730454,
        "longitude": -78.88541208918505,
        "outage_status": "Work assigned",
        "ignore": "",
        "cause_of_outage": null,
        "municipality": "1852",
        "code": ""
    },
    {
        "time_stamp": "2025-06-30 19:21:58",
        "num_of_customers": 1,
        "start_time": "2025-06-30 11:46:55",
        "expected_end_time": "",
        "latitude": 45.49762776607797,
        "longitude": -71.88321632191308,
        "outage_status": "Crew on the way",
        "ignore": "",
        "cause_of_outage": null,
        "municipality": "1529",
        "code": ""
    },
    {
        "time_stamp": "2025-06-30 19:21:58",
        "num_of_customers": 16,
        "start_time": "2025-06-30 14:16:12",
        "expected_end_time": "2025-06-30 16:30:00",
        "latitude": 48.42197014157536,
        "longitude": -71.02597707776056,
        "outage_status": "Crew on the way",
        "ignore": "",
        "cause_of_outage": null,
        "municipality": "1850",
        "code": ""
    },
    {
        "time_stamp": "2025-06-30 19:21:58",
        "num_of_customers": 6,
        "start_time": "2025-06-30 14:36:09",
        "expected_end_time": "2025-06-30 16:30:00",
        "latitude": 45.40730633322991,
        "longitude": -72.20548149593529,
        "outage_status": "Crew at work",
        "ignore": "",
        "cause_of_outage": null,
        "municipality": "5122",
        "code": ""
    },
    {
        "time_stamp": "2025-06-30 19:21:58",
        "num_of_customers": 87,
        "start_time": "2025-06-30 14:53:25",
        "expected_end_time": "",
        "latitude": 46.85927941955187,
        "longitude": -71.18131354404636,
        "outage_status": "NA",
        "ignore": "",
        "cause_of_outage": null,
        "municipality": "1302",
        "code": ""
    },
    {
        "time_stamp": "2025-06-30 19:21:58",
        "num_of_customers": 564,
        "start_time": "2025-06-30 15:07:12",
        "expected_end_time": "",
        "latitude": 46.76554092685293,
        "longitude": -78.94771727353881,
        "outage_status": "NA",
        "ignore": "",
        "cause_of_outage": null,
        "municipality": "9124",
        "code": ""
    },
    {
        "time_stamp": "2025-06-30 19:21:58",
        "num_of_customers": 153,
        "start_time": "2025-06-30 14:54:28",
        "expected_end_time": "",
        "latitude": 46.77489381098655,
        "longitude": -71.25518075439376,
        "outage_status": "NA",
        "ignore": "",
        "cause_of_outage": null,
        "municipality": "5769",
        "code": ""
    },
    {
        "time_stamp": "2025-06-30 19:21:58",
        "num_of_customers": 176,
        "start_time": "2025-06-30 10:03:34",
        "expected_end_time": "2025-06-30 16:15:00",
        "latitude": 45.69622033516757,
        "longitude": -73.59147203043,
        "outage_status": "Crew at work",
        "ignore": "6",
        "cause_of_outage": null,
        "municipality": "6297",
        "code": ""
    },
    {
        "time_stamp": "2025-06-30 19:21:58",
        "num_of_customers": 2,
        "start_time": "2025-06-30 14:33:49",
        "expected_end_time": "2025-06-30 16:30:00",
        "latitude": 45.406908197882984,
        "longitude": -72.20630600845566,
        "outage_status": "Crew at work",
        "ignore": "5",
        "cause_of_outage": "Damage due to vegetation",
        "municipality": "5122",
        "code": ""
    },
    {
        "time_stamp": "2025-06-30 19:21:58",
        "num_of_customers": 17,
        "start_time": "2025-06-30 09:02:37",
        "expected_end_time": "2025-06-30 15:15:00",
        "latitude": 46.6222496308298,
        "longitude": -72.77463296164467,
        "outage_status": "Crew at work",
        "ignore": "6",
        "cause_of_outage": null,
        "municipality": "2435",
        "code": ""
    },
    {
        "time_stamp": "2025-06-30 19:21:58",
        "num_of_customers": 2,
        "start_time": "2025-06-30 09:06:03",
        "expected_end_time": "2025-06-30 15:15:00",
        "latitude": 45.268958567661635,
        "longitude": -73.80831795878278,
        "outage_status": "Crew at work",
        "ignore": "6",
        "cause_of_outage": null,
        "municipality": "7830",
        "code": ""
    },
    {
        "time_stamp": "2025-06-30 19:21:58",
        "num_of_customers": 755,
        "start_time": "2025-06-27 21:19:12",
        "expected_end_time": "2025-06-30 16:15:00",
        "latitude": 45.70593910515177,
        "longitude": -73.93664693783329,
        "outage_status": "Crew at work",
        "ignore": "3",
        "cause_of_outage": "Accident or incident",
        "municipality": "4671",
        "code": ""
    },
    {
        "time_stamp": "2025-06-30 19:21:58",
        "num_of_customers": 36,
        "start_time": "2025-06-30 09:16:01",
        "expected_end_time": "",
        "latitude": 46.34936228663215,
        "longitude": -72.54723527882518,
        "outage_status": "Crew at work",
        "ignore": "6",
        "cause_of_outage": null,
        "municipality": "9233",
        "code": ""
    },
    {
        "time_stamp": "2025-06-30 19:21:58",
        "num_of_customers": 30,
        "start_time": "2025-06-30 09:37:35",
        "expected_end_time": "",
        "latitude": 46.34939485710118,
        "longitude": -72.54715838593359,
        "outage_status": "Crew at work",
        "ignore": "4",
        "cause_of_outage": "Accident or incident",
        "municipality": "9233",
        "code": ""
    },
    {
        "time_stamp": "2025-06-30 19:21:58",
        "num_of_customers": 11,
        "start_time": "2025-06-30 08:09:27",
        "expected_end_time": "2025-06-30 15:45:00",
        "latitude": 46.82776691589429,
        "longitude": -71.01023396944115,
        "outage_status": "Crew at work",
        "ignore": "5",
        "cause_of_outage": "Damage due to vegetation",
        "municipality": "6597",
        "code": ""
    }
]